pyfocus/__init__.py
pyfocus/finemap.py
pyfocus/io.py
pyfocus/util.py
pyfocus/viz.py
pyfocus/data/__init__.py
pyfocus/data/alleles.py
pyfocus/data/exprref.py
pyfocus/data/gwas.py
pyfocus/data/ldref.py
pyfocus/data/gencode/gencode_map_v37.tsv
pyfocus/data/gencode/gencode_map_v38.tsv
pyfocus/data/ld_blocks/grch37.eur.afr.loci.bed
pyfocus/data/ld_blocks/grch37.eur.eas.afr.loci.bed
pyfocus/data/ld_blocks/grch37.eur.eas.loci.bed
pyfocus/data/ld_blocks/grch37.eur.loci.bed
pyfocus/data/ld_blocks/grch38.eur.afr.loci.bed
pyfocus/data/ld_blocks/grch38.eur.eas.afr.loci.bed
pyfocus/data/ld_blocks/grch38.eur.eas.loci.bed
pyfocus/data/ld_blocks/grch38.eur.loci.bed
pyfocus/models/__init__.py
pyfocus/models/convert.py
pyfocus/models/db.py
pyfocus/models/train.py
pyfocus-0.802.data/scripts/focus
pyfocus-0.802.dist-info/._SOURCES.txt
pyfocus-0.802.dist-info/LICENSE
pyfocus-0.802.dist-info/METADATA
pyfocus-0.802.dist-info/WHEEL
pyfocus-0.802.dist-info/top_level.txt
pyfocus-0.802.dist-info/RECORD
