Metadata-Version: 2.1
Name: pyfocus
Version: 0.802
Summary: Fine-map transcriptome-wide association studies
Home-page: https://github.com/mancusolab/focus
Author: Nicholas Mancuso, Ruth Johnson, Zeyun Lu
Author-email: nicholas.mancuso@med.usc.com, ruthjohnson@ucla.com, zeyunlu@usc.edu
License: UNKNOWN
Platform: UNKNOWN
Classifier: Programming Language :: Python :: 3
Classifier: License :: OSI Approved :: GNU General Public License v3 (GPLv3)
Classifier: Operating System :: OS Independent
License-File: LICENSE
Requires-Dist: opencv-python
Requires-Dist: sqlalchemy
Requires-Dist: matplotlib (>=3.1.0)
Requires-Dist: seaborn
Requires-Dist: numpy
Requires-Dist: scipy
Requires-Dist: pandas (>=0.23.0)
Requires-Dist: pandas-plink
